{"nodes": [{"id": "d_code_bluesky_privacy_md", "label": "PRIVACY.md", "file_type": "document", "source_file": "PRIVACY.md", "source_location": "L1"}, {"id": "bluesky_privacy_privacy_policy_for_blubot", "label": "Privacy Policy for BluBot", "file_type": "document", "source_file": "PRIVACY.md", "source_location": "L1"}, {"id": "bluesky_privacy_1_information_we_collect", "label": "1. Information We Collect", "file_type": "document", "source_file": "PRIVACY.md", "source_location": "L7"}, {"id": "bluesky_privacy_2_how_we_use_data", "label": "2. How We Use Data", "file_type": "document", "source_file": "PRIVACY.md", "source_location": "L12"}, {"id": "bluesky_privacy_3_data_sharing_and_third_parties", "label": "3. Data Sharing and Third Parties", "file_type": "document", "source_file": "PRIVACY.md", "source_location": "L18"}, {"id": "bluesky_privacy_4_data_retention", "label": "4. Data Retention", "file_type": "document", "source_file": "PRIVACY.md", "source_location": "L22"}, {"id": "bluesky_privacy_5_revoking_access", "label": "5. Revoking Access", "file_type": "document", "source_file": "PRIVACY.md", "source_location": "L25"}, {"id": "bluesky_privacy_6_contact_support", "label": "6. Contact & Support", "file_type": "document", "source_file": "PRIVACY.md", "source_location": "L30"}], "edges": [{"source": "d_code_bluesky_privacy_md", "target": "bluesky_privacy_privacy_policy_for_blubot", "relation": "contains", "confidence": "EXTRACTED", "source_file": "PRIVACY.md", "source_location": "L1", "weight": 1.0}, {"source": "bluesky_privacy_privacy_policy_for_blubot", "target": "bluesky_privacy_1_information_we_collect", "relation": "contains", "confidence": "EXTRACTED", "source_file": "PRIVACY.md", "source_location": "L7", "weight": 1.0}, {"source": "bluesky_privacy_privacy_policy_for_blubot", "target": "bluesky_privacy_2_how_we_use_data", "relation": "contains", "confidence": "EXTRACTED", "source_file": "PRIVACY.md", "source_location": "L12", "weight": 1.0}, {"source": "bluesky_privacy_privacy_policy_for_blubot", "target": "bluesky_privacy_3_data_sharing_and_third_parties", "relation": "contains", "confidence": "EXTRACTED", "source_file": "PRIVACY.md", "source_location": "L18", "weight": 1.0}, {"source": "bluesky_privacy_privacy_policy_for_blubot", "target": "bluesky_privacy_4_data_retention", "relation": "contains", "confidence": "EXTRACTED", "source_file": "PRIVACY.md", "source_location": "L22", "weight": 1.0}, {"source": "bluesky_privacy_privacy_policy_for_blubot", "target": "bluesky_privacy_5_revoking_access", "relation": "contains", "confidence": "EXTRACTED", "source_file": "PRIVACY.md", "source_location": "L25", "weight": 1.0}, {"source": "bluesky_privacy_privacy_policy_for_blubot", "target": "bluesky_privacy_6_contact_support", "relation": "contains", "confidence": "EXTRACTED", "source_file": "PRIVACY.md", "source_location": "L30", "weight": 1.0}], "input_tokens": 0, "output_tokens": 0}